caesarplus/__init__.py
caesarplus/decrypt.py
caesarplus/encrypt.py
caesarplus-0.1.7.dist-info/LICENSE
caesarplus-0.1.7.dist-info/METADATA
caesarplus-0.1.7.dist-info/WHEEL
caesarplus-0.1.7.dist-info/top_level.txt
caesarplus-0.1.7.dist-info/RECORD
