Metadata-Version: 2.1
Name: caesarplus
Version: 0.1.7
Summary: An advanced caesar cypher python module
Home-page: https://github.com/awesomelewis2007/CaesarPlus/
Author: Lewis Evans
Author-email: awesomelewis2007@gmail.com
License: GNU
Platform: UNKNOWN
License-File: LICENSE
